conftl/__init__.py
conftl/_compat.py
conftl/command_line.py
conftl/core.py
conftl/render_fn.py
conftl/template_decorator.py
conftl-0.5.3.dist-info/LICENSE
conftl-0.5.3.dist-info/METADATA
conftl-0.5.3.dist-info/WHEEL
conftl-0.5.3.dist-info/entry_points.txt
conftl-0.5.3.dist-info/top_level.txt
conftl-0.5.3.dist-info/RECORD
