Metadata-Version: 2.1
Name: conftl
Version: 0.5.3
Summary: Configuration Templating Language
Home-page: https://github.com/ttt-fifo/conftl
Author: Todor Todorov
Author-email: ttodorov@null.net
License: BSD
Project-URL: Bug Reports, https://github.com/ttt-fifo/conftl/issues
Project-URL: Source, https://github.com/ttt-fifo/conftl/
Keywords: templating configuration development sysadmin devops
Platform: UNKNOWN
Classifier: Development Status :: 3 - Alpha
Classifier: Environment :: Console
Classifier: Intended Audience :: Developers
Classifier: Intended Audience :: System Administrators
Classifier: Intended Audience :: Information Technology
Classifier: Intended Audience :: Education
Classifier: Operating System :: OS Independent
Classifier: Topic :: Software Development :: Pre-processors
Classifier: Topic :: System :: Installation/Setup
Classifier: Topic :: System :: Systems Administration
Classifier: Topic :: Text Processing
Classifier: Topic :: Text Processing :: Filters
Classifier: License :: OSI Approved :: BSD License
Classifier: Programming Language :: Python :: 2.7
Classifier: Programming Language :: Python :: 3
Requires-Python: >=2.7, <4
Requires-Dist: future
